freeai_utils/__init__.py
freeai_utils/_setup.py
freeai_utils/apiClient.py
freeai_utils/audio_record.py
freeai_utils/audio_to_text_vn.py
freeai_utils/audio_to_text_whisper.py
freeai_utils/clean_text_for_tts.py
freeai_utils/cleaner.py
freeai_utils/cli.py
freeai_utils/decider.py
freeai_utils/document_filter.py
freeai_utils/geminiAPI.py
freeai_utils/google_search.py
freeai_utils/image_creator.py
freeai_utils/image_to_text.py
freeai_utils/language_detection.py
freeai_utils/live_stt_vosk.py
freeai_utils/localLLM.py
freeai_utils/log_set_up.py
freeai_utils/pdf_docx_reader.py
freeai_utils/scripts.py
freeai_utils/text_from_image_easyocr.py
freeai_utils/text_to_speech_gtts.py
freeai_utils/text_to_speech_pyttsx3.py
freeai_utils/utils.py
freeai_utils-0.6.4.dist-info/licenses/LICENSE
freeai_utils-0.6.4.dist-info/METADATA
freeai_utils-0.6.4.dist-info/WHEEL
freeai_utils-0.6.4.dist-info/entry_points.txt
freeai_utils-0.6.4.dist-info/top_level.txt
freeai_utils-0.6.4.dist-info/RECORD
