Metadata-Version: 2.4
Name: freeai-utils
Version: 0.6.4
Summary: A free, zero-config AI utility toolkit with voice, text, image, and web integrations, pdf_docx readability, decider
Author-email: truongbaan <truongbaansoftware@gmail.com>
License-Expression: MIT
Project-URL: Homepage, https://github.com/truongbaan/Utility-python-library
Classifier: Operating System :: OS Independent
Classifier: Programming Language :: Python :: 3.9
Classifier: Programming Language :: Python :: 3.10
Classifier: Programming Language :: Python :: 3.11
Classifier: Programming Language :: Python :: 3.12
Classifier: Topic :: Scientific/Engineering :: Artificial Intelligence
Requires-Python: >=3.9.13
License-File: LICENSE
Requires-Dist: click
Requires-Dist: python-dotenv
Requires-Dist: requests
Requires-Dist: google-genai
Requires-Dist: numpy
Requires-Dist: langdetect
Requires-Dist: pyperclip
Requires-Dist: Pillow
Requires-Dist: gTTS
Requires-Dist: pyttsx3
Requires-Dist: playsound==1.2.2
Requires-Dist: lameenc
Requires-Dist: librosa
Requires-Dist: mutagen
Requires-Dist: ffmpeg-python
Requires-Dist: imageio-ffmpeg
Requires-Dist: sounddevice
Requires-Dist: keyboard
Requires-Dist: beautifulsoup4
Requires-Dist: readability-lxml
Requires-Dist: pymupdf
Requires-Dist: pypdf
Requires-Dist: pdfplumber
Requires-Dist: python-docx
Requires-Dist: tqdm
Provides-Extra: ai
Requires-Dist: openai-whisper; extra == "ai"
Requires-Dist: vosk; extra == "ai"
Requires-Dist: transformers; extra == "ai"
Requires-Dist: diffusers; extra == "ai"
Requires-Dist: easyocr; extra == "ai"
Requires-Dist: haystack-ai; extra == "ai"
Requires-Dist: peft; extra == "ai"
Requires-Dist: accelerate; extra == "ai"
Requires-Dist: sentencepiece; extra == "ai"
Requires-Dist: protobuf; extra == "ai"
Requires-Dist: ddgs; extra == "ai"
Requires-Dist: translators; extra == "ai"
Requires-Dist: tiktoken; extra == "ai"
Requires-Dist: hf_xet; extra == "ai"
Provides-Extra: all
Requires-Dist: freeai-utils[ai]; extra == "all"
Dynamic: license-file
